twitter_cleaner/__init__.py
twitter_cleaner/__main__.py
twitter_cleaner/app.py
twitter_cleaner/archivefilter.py
twitter_cleaner-0.3.0.dist-info/LICENSE
twitter_cleaner-0.3.0.dist-info/METADATA
twitter_cleaner-0.3.0.dist-info/WHEEL
twitter_cleaner-0.3.0.dist-info/top_level.txt
twitter_cleaner-0.3.0.dist-info/RECORD
