Metadata-Version: 2.1
Name: twitter-cleaner
Version: 0.3.0
Summary: A small python script that allows you to delete your old tweets.
Home-page: https://github.com/fsjunior/twitter_cleaner
Author: Francisco de Souza Junior
Author-email: chico@chico.codes
License: MIT
Platform: UNKNOWN
Classifier: License :: OSI Approved :: GNU General Public License v3 (GPLv3)
Classifier: Programming Language :: Python
Classifier: Programming Language :: Python :: 3
Classifier: Programming Language :: Python :: 3.6
Classifier: Programming Language :: Python :: Implementation :: CPython
Classifier: Programming Language :: Python :: Implementation :: PyPy
Classifier: Environment :: Console
Requires-Python: >=3.6.0
Requires-Dist: pandas
Requires-Dist: tqdm
Requires-Dist: tweepy
